{
  "Web Development": [
    {
      "text": "HTML",
      "logo": "mdi:language-html5"
    },
    {
      "text": "JavaScript",
      "logo": "mdi:language-javascript"
    },
    {
      "text": "TypeScript",
      "logo": "mdi:language-typescript"
    },
    {
      "text": "CSS",
      "logo": "mdi:language-css3"
    },
    {
      "text": "PHP",
      "logo": "mdi:language-php"
    }
  ],
  "Development Tools": [
    {
      "text": "Visual Studio Code",
      "logo": "mdi:visual-studio-code"
    },  
    {
      "text": "Git",
      "logo": "mdi:git"
    }
  ],

  "Operating Systems": [
    {
      "text": "Windows",
      "logo": "mdi:windows"
    },
    {
      "text": "Ubuntu",
      "logo": "mdi:ubuntu"
    },
    {
      "text": "Debian",
      "logo": "mdi:debian"
    },
    {
      "text": "Kali Linux",
      "logo": "mdi:linux"
    }    
  ],
  "Other Programming Languages and Technologies": [
    {
      "text": "Java",
      "logo": "mdi:language-java"
    },
    {
      "text": "Kotlin",
      "logo": "mdi:language-kotlin"
    },
    {
      "text": "C++",
      "logo": "mdi:language-cpp"
    },
    {
      "text": "C#",
      "logo": "mdi:language-c#"
    },
    {
      "text": "Node.js",
      "logo": "mdi:nodejs"
    }
    
  ],
  "Web Servers": [
    {
      "text": "Apache",
      "logo": "cib:apache"
    },
    {
      "text": "Python",
      "logo": "mdi:language-python"
    }
  ],
  "Databases": [
    {
      "text": "MySQL",
      "logo": "cib:mysql"
    },
    {
      "text": "MongoDB",
      "logo": "cib:mongodb"
    }
  ],
  "Other Software": [
    {
      "text": "Visual Studio",
      "logo": "mdi:visual-studio"
    },
    {
      "text": "Brave",
      "logo": "cib:brave"
    }
  ]
}